streamedrequests/__init__.py
streamedrequests/dodownload.py
streamedrequests/exceptions.py
streamedrequests/get.py
streamedrequests/post.py
streamedrequests/responsesize.py
streamedrequests/setuptimeout.py
streamedrequests-1.0.3.dist-info/LICENSE
streamedrequests-1.0.3.dist-info/METADATA
streamedrequests-1.0.3.dist-info/WHEEL
streamedrequests-1.0.3.dist-info/top_level.txt
streamedrequests-1.0.3.dist-info/RECORD
