Metadata-Version: 2.1
Name: streamedrequests
Version: 1.0.3
Summary: Library for streaming http get or post request's responses
Home-page: https://github.com/beardog108/StreamedRequests
Author: Kevin Froman
Author-email: beardog@mailbox.org
License: UNKNOWN
Platform: UNKNOWN
Classifier: Programming Language :: Python :: 3
Classifier: License :: OSI Approved :: GNU General Public License v3 (GPLv3)
Classifier: Operating System :: OS Independent
Requires-Dist: requests
